LICENSE
tiddlyparse/__init__.py
tiddlyparse/parser.py
tiddlyparse-0.2.0.dist-info/LICENSE
tiddlyparse-0.2.0.dist-info/METADATA
tiddlyparse-0.2.0.dist-info/WHEEL
tiddlyparse-0.2.0.dist-info/RECORD
