Metadata-Version: 2.1
Name: TiddlyParse
Version: 0.2.0
Summary: TiddlyParse allows Python to interact with TiddlyWiki files.
Home-page: https://github.com/pneff/TiddlyParse
License: MIT
Author: Patrice Neff
Author-email: mail@patrice.ch
Requires-Python: >=3.9,<4.0
Classifier: Development Status :: 3 - Alpha
Classifier: Environment :: Console
Classifier: License :: OSI Approved :: MIT License
Classifier: Programming Language :: Python :: 3
Classifier: Programming Language :: Python :: 3.9
Classifier: Programming Language :: Python :: 3.10
Classifier: Programming Language :: Python :: 3.11
Requires-Dist: beautifulsoup4 (>=4.12.2,<5.0.0)
Project-URL: Repository, https://github.com/pneff/TiddlyParse
